osprofiler/__init__.py
osprofiler/_utils.py
osprofiler/exc.py
osprofiler/initializer.py
osprofiler/notifier.py
osprofiler/opts.py
osprofiler/profiler.py
osprofiler/requests.py
osprofiler/sqlalchemy.py
osprofiler/web.py
osprofiler/cmd/__init__.py
osprofiler/cmd/cliutils.py
osprofiler/cmd/commands.py
osprofiler/cmd/shell.py
osprofiler/cmd/template.html
osprofiler/drivers/__init__.py
osprofiler/drivers/base.py
osprofiler/drivers/elasticsearch_driver.py
osprofiler/drivers/jaeger.py
osprofiler/drivers/loginsight.py
osprofiler/drivers/messaging.py
osprofiler/drivers/mongodb.py
osprofiler/drivers/otlp.py
osprofiler/drivers/redis_driver.py
osprofiler/drivers/sqlalchemy_driver.py
osprofiler/hacking/__init__.py
osprofiler/hacking/checks.py
osprofiler/tests/__init__.py
osprofiler/tests/test.py
osprofiler/tests/functional/__init__.py
osprofiler/tests/functional/config.cfg
osprofiler/tests/functional/test_driver.py
osprofiler/tests/unit/__init__.py
osprofiler/tests/unit/test_initializer.py
osprofiler/tests/unit/test_notifier.py
osprofiler/tests/unit/test_opts.py
osprofiler/tests/unit/test_profiler.py
osprofiler/tests/unit/test_sqlalchemy.py
osprofiler/tests/unit/test_utils.py
osprofiler/tests/unit/test_web.py
osprofiler/tests/unit/cmd/__init__.py
osprofiler/tests/unit/cmd/test_shell.py
osprofiler/tests/unit/doc/__init__.py
osprofiler/tests/unit/doc/test_specs.py
osprofiler/tests/unit/drivers/__init__.py
osprofiler/tests/unit/drivers/test_base.py
osprofiler/tests/unit/drivers/test_elasticsearch.py
osprofiler/tests/unit/drivers/test_jaeger.py
osprofiler/tests/unit/drivers/test_loginsight.py
osprofiler/tests/unit/drivers/test_messaging.py
osprofiler/tests/unit/drivers/test_mongodb.py
osprofiler/tests/unit/drivers/test_otlp.py
osprofiler/tests/unit/drivers/test_redis_driver.py
osprofiler-4.3.0.dist-info/AUTHORS
osprofiler-4.3.0.dist-info/LICENSE
osprofiler-4.3.0.dist-info/METADATA
osprofiler-4.3.0.dist-info/WHEEL
osprofiler-4.3.0.dist-info/entry_points.txt
osprofiler-4.3.0.dist-info/pbr.json
osprofiler-4.3.0.dist-info/top_level.txt
osprofiler-4.3.0.dist-info/RECORD
