Metadata-Version: 2.1
Name: osprofiler
Version: 4.3.0
Summary: OpenStack Profiler Library
Home-page: https://docs.openstack.org/osprofiler/latest/
Author: OpenStack
Author-email: openstack-discuss@lists.openstack.org
Classifier: Environment :: OpenStack
Classifier: Intended Audience :: Developers
Classifier: Intended Audience :: Information Technology
Classifier: License :: OSI Approved :: Apache Software License
Classifier: Operating System :: POSIX :: Linux
Classifier: Programming Language :: Python
Classifier: Programming Language :: Python :: 3
Classifier: Programming Language :: Python :: 3.9
Classifier: Programming Language :: Python :: 3.10
Classifier: Programming Language :: Python :: 3.11
Classifier: Programming Language :: Python :: 3.12
Classifier: Programming Language :: Python :: 3 :: Only
Classifier: Programming Language :: Python :: Implementation :: CPython
Requires-Python: >=3.9
License-File: LICENSE
Requires-Dist: netaddr>=0.7.18
Requires-Dist: oslo.concurrency>=3.26.0
Requires-Dist: oslo.config>=5.2.0
Requires-Dist: oslo.serialization>=2.18.0
Requires-Dist: oslo.utils>=3.33.0
Requires-Dist: PrettyTable>=0.7.2
Requires-Dist: requests>=2.14.2
Requires-Dist: WebOb>=1.7.1
Provides-Extra: elasticsearch
Requires-Dist: elasticsearch>=2.0.0; extra == "elasticsearch"
Provides-Extra: jaeger
Requires-Dist: jaeger-client>=3.8.0; extra == "jaeger"
Provides-Extra: messaging
Requires-Dist: oslo.messaging>=14.1.0; extra == "messaging"
Provides-Extra: mongo
Requires-Dist: pymongo!=3.1,>=3.0.2; extra == "mongo"
Provides-Extra: otlp
Requires-Dist: opentelemetry-exporter-otlp>=1.16.0; extra == "otlp"
Requires-Dist: opentelemetry-sdk>=1.16.0; extra == "otlp"
Provides-Extra: redis
Requires-Dist: redis>=2.10.0; extra == "redis"
Provides-Extra: sqlalchemy
Requires-Dist: SQLAlchemy>=1.4.0; extra == "sqlalchemy"
Provides-Extra: test
Requires-Dist: coverage>=4.0; extra == "test"
Requires-Dist: ddt>=1.0.1; extra == "test"
Requires-Dist: stestr>=2.0.0; extra == "test"
Requires-Dist: testtools>=2.2.0; extra == "test"
Requires-Dist: docutils>=0.14; extra == "test"
Requires-Dist: pymongo!=3.1,>=3.0.2; extra == "test"
Requires-Dist: elasticsearch>=2.0.0; extra == "test"
Requires-Dist: redis>=2.10.0; extra == "test"
Requires-Dist: jaeger-client>=3.8.0; extra == "test"
Requires-Dist: opentelemetry-exporter-otlp>=1.16.0; extra == "test"
Requires-Dist: opentelemetry-sdk>=1.16.0; extra == "test"
